{
  "swagger": "2.0",
  "info": {
    "title": "api.proto",
    "version": "version not set"
  },
  "consumes": [
    "application/json"
  ],
  "produces": [
    "application/json"
  ],
  "paths": {
    "/v1/auth/signin": {
      "post": {
        "operationId": "Login",
        "responses": {
          "200": {
            "description": "A successful response.",
            "schema": {
              "$ref": "#/definitions/protoLoginResponse"
            }
          }
        },
        "parameters": [
          {
            "name": "body",
            "in": "body",
            "required": true,
            "schema": {
              "$ref": "#/definitions/protoLoginRequest"
            }
          }
        ],
        "tags": [
          "AuthService"
        ]
      }
    },
    "/v1/authping": {
      "post": {
        "operationId": "SayHellogw",
        "responses": {
          "200": {
            "description": "A successful response.",
            "schema": {
              "$ref": "#/definitions/protoPingMessage"
            }
          }
        },
        "parameters": [
          {
            "name": "body",
            "in": "body",
            "required": true,
            "schema": {
              "$ref": "#/definitions/protoPingMessage"
            }
          }
        ],
        "tags": [
          "AuthService"
        ]
      }
    }
  },
  "definitions": {
    "protoLoginRequest": {
      "type": "object",
      "properties": {
        "username": {
          "type": "string"
        },
        "password": {
          "type": "string"
        }
      }
    },
    "protoLoginResponse": {
      "type": "object",
      "properties": {
        "access_token": {
          "type": "string"
        }
      }
    },
    "protoPingMessage": {
      "type": "object",
      "properties": {
        "greeting": {
          "type": "string"
        }
      }
    }
  }
}
